livesearch/__init__.py
livesearch-1.1.0.dist-info/licenses/LICENSE
livesearch-1.1.0.dist-info/METADATA
livesearch-1.1.0.dist-info/WHEEL
livesearch-1.1.0.dist-info/top_level.txt
livesearch-1.1.0.dist-info/RECORD
