Metadata-Version: 2.4
Name: livesearch
Version: 1.1.0
Summary: Add your description here
Requires-Python: >=3.10
License-File: LICENSE
Dynamic: license-file
